CHANGELOG.txt
LICENSE.txt
MANIFEST.in
README.txt
setup.py
classification_model/VERSION
classification_model/__init__.py
classification_model/pipeline.py
classification_model/predict.py
classification_model/train_pipeline.py
classification_model/config/__init__.py
classification_model/config/core.py
classification_model/datasets/__init__.py
classification_model/datasets/test.csv
classification_model/datasets/train.csv
classification_model/preprocessing/__init__.py
classification_model/preprocessing/data_manager.py
classification_model/preprocessing/modelevaluation.py
classification_model/preprocessing/preprocessing.py
classification_model/preprocessing/validation.py
classification_model/trained_models/__init__.py
classification_model/trained_models/classification_model_output_v0.0.4.h5
classification_model/trained_models/classification_model_output_v0.0.4.joblib
classification_model/trained_models/classification_model_output_v_preprocess0.0.4.joblib
consumer_complaint_classification_model.egg-info/PKG-INFO
consumer_complaint_classification_model.egg-info/SOURCES.txt
consumer_complaint_classification_model.egg-info/dependency_links.txt
consumer_complaint_classification_model.egg-info/requires.txt
consumer_complaint_classification_model.egg-info/top_level.txt