Metadata-Version: 2.1
Name: consumer-complaint-classification-model
Version: 0.0.4
Summary: Classification of consumer complaint.
Home-page: https://github.com/KrSiddhartha/MLPipeline/
Author: KumarSiddhartha
Author-email: kr.siddhartha91@gmail.com
License: BSD-3
Platform: UNKNOWN
Classifier: License :: OSI Approved :: MIT License
Classifier: Programming Language :: Python
Classifier: Programming Language :: Python :: 3
Classifier: Programming Language :: Python :: 3.6
Classifier: Programming Language :: Python :: 3.7
Classifier: Programming Language :: Python :: 3.8
Classifier: Programming Language :: Python :: 3.9
Classifier: Programming Language :: Python :: Implementation :: CPython
Classifier: Programming Language :: Python :: Implementation :: PyPy
Requires-Python: ==3.8.5
